pdf_chunker_for_rag/__init__.py
pdf_chunker_for_rag/chunk_creator.py
pdf_chunker_for_rag-2.0.0.dist-info/METADATA
pdf_chunker_for_rag-2.0.0.dist-info/WHEEL
pdf_chunker_for_rag-2.0.0.dist-info/top_level.txt
pdf_chunker_for_rag-2.0.0.dist-info/RECORD
