Metadata-Version: 2.1
Name: pdf_chunker_for_rag
Version: 2.0.0
Summary: Production-ready PDF chunking library with intelligent content filtering and strategic header detection
Home-page: https://github.com/your-username/chunk_creation
Author: AI Assistant
Author-email: assistant@example.com
Classifier: Development Status :: 5 - Production/Stable
Classifier: Intended Audience :: Developers
Classifier: Intended Audience :: Science/Research
Classifier: License :: OSI Approved :: MIT License
Classifier: Operating System :: OS Independent
Classifier: Programming Language :: Python :: 3
Classifier: Programming Language :: Python :: 3.8
Classifier: Programming Language :: Python :: 3.9
Classifier: Programming Language :: Python :: 3.10
Classifier: Programming Language :: Python :: 3.11
Classifier: Programming Language :: Python :: 3.12
Classifier: Topic :: Text Processing
Classifier: Topic :: Scientific/Engineering :: Information Analysis
Classifier: Topic :: Software Development :: Libraries :: Python Modules
Requires-Python: >=3.8
Requires-Dist: PyMuPDF>=1.23.0
Requires-Dist: pypdf>=3.0.0
Provides-Extra: nlp
Requires-Dist: spacy>=3.5.0; extra == "nlp"
Provides-Extra: dev
Requires-Dist: pytest>=7.0.0; extra == "dev"
Requires-Dist: black>=23.0.0; extra == "dev"
Requires-Dist: isort>=5.12.0; extra == "dev"
Requires-Dist: flake8>=6.0.0; extra == "dev"
